mvwt/__init__.py
mvwt/cli.py
mvwt/flycheck_plotting.py
mvwt/mvwt.py
mvwt/plotting.py
mvwt/__pycache__/mvwt.cpython-313.pyc
mvwt-0.4.0.dist-info/AUTHORS.rst
mvwt-0.4.0.dist-info/LICENSE
mvwt-0.4.0.dist-info/METADATA
mvwt-0.4.0.dist-info/WHEEL
mvwt-0.4.0.dist-info/entry_points.txt
mvwt-0.4.0.dist-info/top_level.txt
mvwt-0.4.0.dist-info/RECORD
