Metadata-Version: 2.1
Name: mvwt
Version: 0.4.0
Summary: Minimum viable weight tracker
Home-page: https://github.com/Craskermasker/mvwt
Author: Evan C Edmond
Author-email: eedmond@gmail.com
License: GNU General Public License v3
Keywords: mvwt
Classifier: Development Status :: 2 - Pre-Alpha
Classifier: Intended Audience :: Developers
Classifier: License :: OSI Approved :: GNU General Public License v3 (GPLv3)
Classifier: Natural Language :: English
Classifier: Programming Language :: Python :: 3
Classifier: Programming Language :: Python :: 3.5
Classifier: Programming Language :: Python :: 3.6
Classifier: Programming Language :: Python :: 3.7
Classifier: Programming Language :: Python :: 3.8
Requires-Python: >=3.5
License-File: LICENSE
License-File: AUTHORS.rst
